[
  {
    "timestamp": "22. Oktober 2025, 12:24 Uhr",
    "status": "online"
  },
  {
    "timestamp": "22. Oktober 2025, 13:07 Uhr",
    "status": "online"
  },
  {
    "timestamp": "22. Oktober 2025, 13:43 Uhr",
    "status": "online"
  },
  {
    "timestamp": "22. Oktober 2025, 13:54 Uhr",
    "status": "online"
  },
  {
    "timestamp": "22. Oktober 2025, 14:13 Uhr",
    "status": "online"
  },
  {
    "timestamp": "22. Oktober 2025, 14:38 Uhr",
    "status": "online"
  },
  {
    "timestamp": "22. Oktober 2025, 14:53 Uhr",
    "status": "online"
  },
  {
    "timestamp": "22. Oktober 2025, 15:11 Uhr",
    "status": "online"
  },
  {
    "timestamp": "22. Oktober 2025, 15:32 Uhr",
    "status": "online"
  },
  {
    "timestamp": "22. Oktober 2025, 15:47 Uhr",
    "status": "online"
  },
  {
    "timestamp": "22. Oktober 2025, 16:15 Uhr",
    "status": "online"
  },
  {
    "timestamp": "22. Oktober 2025, 16:46 Uhr",
    "status": "online"
  },
  {
    "timestamp": "22. Oktober 2025, 17:11 Uhr",
    "status": "online"
  },
  {
    "timestamp": "22. Oktober 2025, 17:28 Uhr",
    "status": "online"
  },
  {
    "timestamp": "22. Oktober 2025, 17:38 Uhr",
    "status": "online"
  },
  {
    "timestamp": "22. Oktober 2025, 17:47 Uhr",
    "status": "online"
  },
  {
    "timestamp": "22. Oktober 2025, 18:18 Uhr",
    "status": "online"
  },
  {
    "timestamp": "22. Oktober 2025, 18:48 Uhr",
    "status": "online"
  },
  {
    "timestamp": "22. Oktober 2025, 19:09 Uhr",
    "status": "online"
  },
  {
    "timestamp": "22. Oktober 2025, 19:22 Uhr",
    "status": "online"
  },
  {
    "timestamp": "22. Oktober 2025, 19:33 Uhr",
    "status": "online"
  },
  {
    "timestamp": "22. Oktober 2025, 19:47 Uhr",
    "status": "online"
  },
  {
    "timestamp": "22. Oktober 2025, 20:14 Uhr",
    "status": "online"
  },
  {
    "timestamp": "22. Oktober 2025, 20:33 Uhr",
    "status": "online"
  },
  {
    "timestamp": "22. Oktober 2025, 20:47 Uhr",
    "status": "online"
  },
  {
    "timestamp": "22. Oktober 2025, 21:09 Uhr",
    "status": "online"
  },
  {
    "timestamp": "22. Oktober 2025, 21:22 Uhr",
    "status": "online"
  },
  {
    "timestamp": "22. Oktober 2025, 21:33 Uhr",
    "status": "online"
  },
  {
    "timestamp": "22. Oktober 2025, 21:47 Uhr",
    "status": "online"
  },
  {
    "timestamp": "22. Oktober 2025, 22:09 Uhr",
    "status": "online"
  },
  {
    "timestamp": "22. Oktober 2025, 22:26 Uhr",
    "status": "online"
  },
  {
    "timestamp": "22. Oktober 2025, 22:34 Uhr",
    "status": "online"
  },
  {
    "timestamp": "22. Oktober 2025, 22:47 Uhr",
    "status": "online"
  },
  {
    "timestamp": "22. Oktober 2025, 23:09 Uhr",
    "status": "online"
  },
  {
    "timestamp": "22. Oktober 2025, 23:25 Uhr",
    "status": "online"
  },
  {
    "timestamp": "22. Oktober 2025, 23:33 Uhr",
    "status": "online"
  },
  {
    "timestamp": "22. Oktober 2025, 23:47 Uhr",
    "status": "online"
  },
  {
    "timestamp": "23. Oktober 2025, 00:56 Uhr",
    "status": "online"
  },
  {
    "timestamp": "23. Oktober 2025, 02:23 Uhr",
    "status": "online"
  },
  {
    "timestamp": "23. Oktober 2025, 03:23 Uhr",
    "status": "online"
  },
  {
    "timestamp": "23. Oktober 2025, 03:47 Uhr",
    "status": "online"
  },
  {
    "timestamp": "23. Oktober 2025, 04:14 Uhr",
    "status": "online"
  },
  {
    "timestamp": "23. Oktober 2025, 04:34 Uhr",
    "status": "online"
  },
  {
    "timestamp": "23. Oktober 2025, 04:49 Uhr",
    "status": "online"
  },
  {
    "timestamp": "23. Oktober 2025, 05:12 Uhr",
    "status": "online"
  },
  {
    "timestamp": "23. Oktober 2025, 05:31 Uhr",
    "status": "online"
  },
  {
    "timestamp": "23. Oktober 2025, 05:47 Uhr",
    "status": "online"
  },
  {
    "timestamp": "23. Oktober 2025, 06:18 Uhr",
    "status": "online"
  },
  {
    "timestamp": "23. Oktober 2025, 06:47 Uhr",
    "status": "online"
  },
  {
    "timestamp": "23. Oktober 2025, 07:12 Uhr",
    "status": "online"
  },
  {
    "timestamp": "23. Oktober 2025, 07:29 Uhr",
    "status": "online"
  },
  {
    "timestamp": "23. Oktober 2025, 07:39 Uhr",
    "status": "online"
  },
  {
    "timestamp": "23. Oktober 2025, 07:47 Uhr",
    "status": "online"
  },
  {
    "timestamp": "23. Oktober 2025, 08:17 Uhr",
    "status": "online"
  },
  {
    "timestamp": "23. Oktober 2025, 08:45 Uhr",
    "status": "online"
  },
  {
    "timestamp": "23. Oktober 2025, 09:13 Uhr",
    "status": "online"
  },
  {
    "timestamp": "23. Oktober 2025, 09:32 Uhr",
    "status": "online"
  },
  {
    "timestamp": "23. Oktober 2025, 09:48 Uhr",
    "status": "online"
  },
  {
    "timestamp": "23. Oktober 2025, 10:13 Uhr",
    "status": "online"
  },
  {
    "timestamp": "23. Oktober 2025, 10:36 Uhr",
    "status": "online"
  },
  {
    "timestamp": "23. Oktober 2025, 10:48 Uhr",
    "status": "online"
  },
  {
    "timestamp": "23. Oktober 2025, 11:10 Uhr",
    "status": "online"
  },
  {
    "timestamp": "23. Oktober 2025, 11:26 Uhr",
    "status": "online"
  },
  {
    "timestamp": "23. Oktober 2025, 11:35 Uhr",
    "status": "online"
  },
  {
    "timestamp": "23. Oktober 2025, 11:47 Uhr",
    "status": "online"
  },
  {
    "timestamp": "23. Oktober 2025, 12:24 Uhr",
    "status": "online"
  },
  {
    "timestamp": "23. Oktober 2025, 13:05 Uhr",
    "status": "online"
  },
  {
    "timestamp": "23. Oktober 2025, 13:42 Uhr",
    "status": "online"
  },
  {
    "timestamp": "23. Oktober 2025, 13:52 Uhr",
    "status": "online"
  },
  {
    "timestamp": "23. Oktober 2025, 14:12 Uhr",
    "status": "online"
  },
  {
    "timestamp": "23. Oktober 2025, 14:35 Uhr",
    "status": "online"
  },
  {
    "timestamp": "23. Oktober 2025, 14:51 Uhr",
    "status": "online"
  },
  {
    "timestamp": "23. Oktober 2025, 15:12 Uhr",
    "status": "offline"
  },
  {
    "timestamp": "23. Oktober 2025, 15:31 Uhr",
    "status": "online"
  },
  {
    "timestamp": "23. Oktober 2025, 15:47 Uhr",
    "status": "online"
  },
  {
    "timestamp": "23. Oktober 2025, 16:14 Uhr",
    "status": "online"
  },
  {
    "timestamp": "23. Oktober 2025, 16:40 Uhr",
    "status": "online"
  },
  {
    "timestamp": "23. Oktober 2025, 16:53 Uhr",
    "status": "online"
  },
  {
    "timestamp": "23. Oktober 2025, 17:10 Uhr",
    "status": "online"
  },
  {
    "timestamp": "23. Oktober 2025, 17:29 Uhr",
    "status": "online"
  },
  {
    "timestamp": "23. Oktober 2025, 17:40 Uhr",
    "status": "online"
  },
  {
    "timestamp": "23. Oktober 2025, 17:47 Uhr",
    "status": "online"
  },
  {
    "timestamp": "23. Oktober 2025, 18:17 Uhr",
    "status": "online"
  },
  {
    "timestamp": "23. Oktober 2025, 18:46 Uhr",
    "status": "online"
  },
  {
    "timestamp": "23. Oktober 2025, 19:09 Uhr",
    "status": "online"
  },
  {
    "timestamp": "23. Oktober 2025, 19:24 Uhr",
    "status": "online"
  },
  {
    "timestamp": "23. Oktober 2025, 19:33 Uhr",
    "status": "online"
  },
  {
    "timestamp": "23. Oktober 2025, 19:47 Uhr",
    "status": "online"
  },
  {
    "timestamp": "23. Oktober 2025, 20:13 Uhr",
    "status": "online"
  },
  {
    "timestamp": "23. Oktober 2025, 20:31 Uhr",
    "status": "online"
  },
  {
    "timestamp": "23. Oktober 2025, 20:47 Uhr",
    "status": "online"
  },
  {
    "timestamp": "23. Oktober 2025, 21:10 Uhr",
    "status": "online"
  },
  {
    "timestamp": "23. Oktober 2025, 21:24 Uhr",
    "status": "online"
  },
  {
    "timestamp": "23. Oktober 2025, 21:33 Uhr",
    "status": "online"
  },
  {
    "timestamp": "23. Oktober 2025, 21:47 Uhr",
    "status": "online"
  },
  {
    "timestamp": "23. Oktober 2025, 22:11 Uhr",
    "status": "online"
  }
]
